hypellm/__init__.py
hypellm/helpers.py
hypellm/recipes.py
hypellm/settings.py
hypellm/types.py
hypellm/impl/__init__.py
hypellm/impl/dspy/__init__.py
hypellm/impl/dspy/base.py
hypellm/impl/dspy/inferred.py
hypellm/impl/dspy/questions.py
hypellm/impl/dspy/reasoned.py
hypellm/impl/instructor/__init__.py
hypellm/impl/instructor/base.py
hypellm/impl/instructor/inferred.py
hypellm/impl/instructor/questions.py
hypellm/impl/instructor/reasoned.py
hypellm-0.0.4.dist-info/METADATA
hypellm-0.0.4.dist-info/WHEEL
hypellm-0.0.4.dist-info/licenses/LICENSE
hypellm-0.0.4.dist-info/RECORD
