Metadata-Version: 2.3
Name: hypellm
Version: 0.0.4
Summary: A toolkit for LLM data augmentation
Author-email: Cyrus Nouroozi <cyrus@zenbase.ai>
Requires-Python: >=3.8
Requires-Dist: asyncer==0.0.8
Requires-Dist: pydantic-settings>=2.0
Requires-Dist: pydantic>=2.0
